awxapis/__init__.py
awxapis/config.py
awxapis/execute.py
awxapis/inventory.py
awxapis/job.py
awxapis/login.py
awxapis/project.py
awxapis/template.py
awxapis-0.6.dist-info/METADATA
awxapis-0.6.dist-info/WHEEL
awxapis-0.6.dist-info/top_level.txt
awxapis-0.6.dist-info/RECORD
