Metadata-Version: 2.1
Name: awxapis
Version: 0.6
Summary: Helper module for utilizing Ansible Tower/AWX Apis
Home-page: https://github.com/nirabhratapaswi/awx-apis
Author: Nirabhra Tapaswi
Author-email: nirabhratapaswi@gmail.com
License: UNKNOWN
Platform: UNKNOWN
Classifier: Programming Language :: Python :: 3
Classifier: License :: OSI Approved :: MIT License
Classifier: Operating System :: OS Independent
Requires-Dist: requests
Requires-Dist: beautifulsoup4
